videohash2/__init__.py
videohash2/__version__.py
videohash2/collagemaker.py
videohash2/downloader.py
videohash2/exceptions.py
videohash2/framesextractor.py
videohash2/tilemaker.py
videohash2/utils.py
videohash2/videocopy.py
videohash2/videoduration.py
videohash2/videohash.py
videohash2-3.2.2.dist-info/LICENSE
videohash2-3.2.2.dist-info/METADATA
videohash2-3.2.2.dist-info/WHEEL
videohash2-3.2.2.dist-info/top_level.txt
videohash2-3.2.2.dist-info/RECORD
