Metadata-Version: 2.1
Name: videohash2
Version: 3.2.2
Summary: Python package for Near Duplicate Video Detection (Perceptual Video Hashing) - Get a 64-bit comparable hash-value for any video.
Home-page: https://demmenie.github.io/videohash2/
Download-URL: https://github.com/demmenie/videohash2/archive/3.2.2.tar.gz
Author: Akash Mahanty and Chico Demmenie
Author-email: cdemmenie@gmail.com
License: MIT
Project-URL: Source, https://github.com/demmenie/videohash2
Project-URL: Documentation, https://github.com/demmenie/videohash2/wiki
Project-URL: Tracker, https://github.com/demmenie/videohash2/issues
Keywords: videohash2,near duplicate video detection,NDVD,perceptual video hashing,video hashing,near duplicate video,compare videos,video,video diff
Classifier: Development Status :: 5 - Production/Stable
Classifier: Intended Audience :: Developers
Classifier: Intended Audience :: End Users/Desktop
Classifier: Intended Audience :: Information Technology
Classifier: Operating System :: MacOS
Classifier: Operating System :: Microsoft :: Windows
Classifier: Operating System :: POSIX
Classifier: Operating System :: POSIX :: Linux
Classifier: Operating System :: POSIX :: BSD
Classifier: Topic :: Multimedia :: Video
Classifier: Natural Language :: English
Classifier: Topic :: Software Development :: Build Tools
Classifier: Topic :: Scientific/Engineering :: Image Recognition
Classifier: Typing :: Typed
Classifier: License :: OSI Approved :: MIT License
Classifier: Programming Language :: Python
Classifier: Programming Language :: Python :: 3
Classifier: Programming Language :: Python :: 3.8
Classifier: Programming Language :: Python :: 3.9
Classifier: Programming Language :: Python :: 3.10
Classifier: Programming Language :: Python :: 3.11
Classifier: Programming Language :: Python :: Implementation :: CPython
Requires-Python: >=3.6
License-File: LICENSE
Requires-Dist: ImageHash
Requires-Dist: Pillow
Requires-Dist: imagedominantcolour
Requires-Dist: yt-dlp
